cc__came.py
cc_came-1.0.dist-info/METADATA
cc_came-1.0.dist-info/WHEEL
cc_came-1.0.dist-info/top_level.txt
cc_came-1.0.dist-info/RECORD
