Metadata-Version: 2.1
Name: cc-came
Version: 1.0
Summary: zuozhe
Home-page: UNKNOWN
Author: Mis__qiaoyun
Author-email: 3233175474@qq.com
License: UNKNOWN
Platform: UNKNOWN
